__main__.py
main.py
windows_mcp_entry.py
src/__init__.py
src/desktop/__init__.py
src/desktop/config.py
src/desktop/views.py
src/tree/__init__.py
src/tree/config.py
src/tree/utils.py
src/tree/views.py
windows_mcp_server-0.1.5.dist-info/licenses/LICENSE
windows_mcp_server-0.1.5.dist-info/METADATA
windows_mcp_server-0.1.5.dist-info/WHEEL
windows_mcp_server-0.1.5.dist-info/entry_points.txt
windows_mcp_server-0.1.5.dist-info/top_level.txt
windows_mcp_server-0.1.5.dist-info/RECORD
