Metadata-Version: 2.4
Name: windows-mcp-server
Version: 0.1.5
Summary: Lightweight MCP Server for interacting with Windows Operating System.
Author-email: Jeomon George <jeogeoalukka@gmail.com>
License: MIT License
Project-URL: homepage, https://github.com/danielsimonjr/Windows-MCP
Keywords: windows,mcp,ai,desktop,ai agent
Requires-Python: >=3.13
License-File: LICENSE
Requires-Dist: fastmcp>=2.8.1
Requires-Dist: fuzzywuzzy>=0.18.0
Requires-Dist: humancursor>=1.1.5
Requires-Dist: markdownify>=1.1.0
Requires-Dist: pillow>=11.2.1
Requires-Dist: pyautogui>=0.9.54
Requires-Dist: python-levenshtein>=0.27.1
Requires-Dist: requests>=2.32.3
Requires-Dist: uiautomation>=2.0.24
Requires-Dist: pyperclip>=1.8.2
Dynamic: license-file
